{
  "symbol": "MNQ",
  "timeframe": "1H",
  "chunkSize": 5000,
  "totalCandles": 11731,
  "totalChunks": 3,
  "firstDate": "2024-01-01",
  "lastDate": "2025-12-26",
  "firstTime": 1704150000,
  "lastTime": 1766782800,
  "chunks": [
    {
      "file": "chunk-0.json",
      "index": 0,
      "count": 5000,
      "firstDate": "2024-01-01",
      "lastDate": "2024-11-04",
      "firstTime": 1704150000,
      "lastTime": 1730718000
    },
    {
      "file": "chunk-1.json",
      "index": 1,
      "count": 5000,
      "firstDate": "2024-11-04",
      "lastDate": "2025-09-10",
      "firstTime": 1730721600,
      "lastTime": 1757523600
    },
    {
      "file": "chunk-2.json",
      "index": 2,
      "count": 1731,
      "firstDate": "2025-09-10",
      "lastDate": "2025-12-26",
      "firstTime": 1757527200,
      "lastTime": 1766782800
    }
  ]
}